pushcollector/__init__.py
pushcollector/_impl/__init__.py
pushcollector/_impl/collector.py
pushcollector/_impl/dummy.py
pushcollector/_impl/local.py
pushcollector/_impl/proxy.py
pushcollector/_impl/schema/__init__.py
pushcollector/_impl/schema/pushitem.yaml
pushcollector-1.3.0.dist-info/LICENSE
pushcollector-1.3.0.dist-info/METADATA
pushcollector-1.3.0.dist-info/WHEEL
pushcollector-1.3.0.dist-info/top_level.txt
pushcollector-1.3.0.dist-info/RECORD
