Metadata-Version: 2.1
Name: pushcollector
Version: 1.3.0
Summary: A library to collect information from push tasks
Home-page: https://github.com/release-engineering/pushcollector
License: GNU General Public License
Project-URL: Documentation, https://release-engineering.github.io/pushcollector/
Project-URL: Changelog, https://github.com/release-engineering/pushcollector/blob/master/CHANGELOG.md
Platform: UNKNOWN
Classifier: Development Status :: 4 - Beta
Classifier: Intended Audience :: Developers
Classifier: License :: OSI Approved :: GNU General Public License v3 or later (GPLv3+)
Classifier: Programming Language :: Python :: 2
Classifier: Programming Language :: Python :: 2.6
Classifier: Programming Language :: Python :: 2.7
Classifier: Programming Language :: Python :: 3
Classifier: Topic :: Software Development :: Libraries :: Python Modules
Requires-Python: >=2.6
Requires-Dist: jsonschema
Requires-Dist: more-executors (>=2.1.0)
Requires-Dist: PyYAML
